{
  "slug": "international-coffee-day",
  "locale": "ar",
  "capturedAt": "2026-07-10T15:20:20.173Z",
  "primaryQueries": [
    "متى اليوم العالمي للقهوة {{year}}",
    "1 أكتوبر اليوم العالمي للقهوة",
    "لماذا 1 أكتوبر يوم القهوة العالمي",
    "منظمة القهوة الدولية",
    "القهوة العربية اليونسكو",
    "الفرق بين القهوة العربية والقهوة السعودية",
    "من أسس اليوم العالمي للقهوة",
    "هل القهوة العربية مسجلة في اليونسكو",
    "كم باقي على اليوم العالمي للقهوة {{year}}",
    "اليوم العالمي للقهوة {{nextYear}}"
  ],
  "competitors": [
    {
      "site": "ar.wikipedia.org",
      "type": "reference",
      "url": "https://ar.wikipedia.org/wiki/اليوم_العالمي_للقهوة",
      "focus": [
        "مرجع أساسي عن تأسيس اليوم ومنظمة القهوة الدولية"
      ],
      "gaps": [
        "لا يوجد عداد أو محتوى يتجدد سنوياً",
        "لا يربط اليوم بقصة القهوة العربية في اليونسكو"
      ]
    },
    {
      "site": "akhbaar24.com",
      "type": "arabic-competitor",
      "url": "https://www.akhbaar24.com/article/detail/619267",
      "focus": [
        "مقال يشرح قصة اليوم ومتى بدأ الاحتفال به"
      ],
      "gaps": [
        "محتوى إخباري موسمي يختفي بعد أيام، لا يجيب عن سؤال الفرق بين القهوة العربية والسعودية"
      ]
    },
    {
      "site": "aawsat.com",
      "type": "arabic-competitor",
      "url": "https://aawsat.com/home/article/1411786/في-اليوم-العالمي-للقهوة-أين-ومتى-اكتشفت",
      "focus": [
        "مقال عن أصل اكتشاف القهوة تاريخياً"
      ],
      "gaps": [
        "يركز على أصل اكتشاف القهوة عموماً، لا على اليوم العالمي أو القهوة العربية تحديداً"
      ]
    },
    {
      "site": "vetogate.com",
      "type": "arabic-competitor",
      "url": "https://www.vetogate.com/5250653",
      "focus": [
        "يشرح تاريخ اليوم وفوائد القهوة وسبب اختيار تاريخ الاحتفال"
      ],
      "gaps": [
        "لا يذكر تسجيل القهوة العربية في اليونسكو إطلاقاً"
      ]
    },
    {
      "site": "sayidaty.net",
      "type": "arabic-competitor",
      "url": "https://www.sayidaty.net/بلس/ثقافة-وفنون/1821104-اليوم-العالمي-للقهوة",
      "focus": [
        "تغطية سنوية متكررة لليوم العالمي للقهوة بزاوية ثقافية"
      ],
      "gaps": [
        "مقال إخباري سنوي عام دون تركيز على الفرق بين القهوة العربية والسعودية"
      ]
    },
    {
      "site": "akhbarelyom.com",
      "type": "arabic-competitor",
      "url": "https://akhbarelyom.com/news/newdetails/3895375/1/في-اليوم-العالمي-للقهوة-التاريخ-والأهمية",
      "focus": [
        "مقال شامل عن تاريخ اليوم وأهميته"
      ],
      "gaps": [
        "لا يفصل بدقة بين القهوة العربية (تسجيل يونسكو) والقهوة السعودية (اسم محلي)"
      ]
    },
    {
      "site": "ich.unesco.org",
      "type": "official",
      "url": "https://ich.unesco.org/en/RL/arabic-coffee-a-symbol-of-generosity-01074",
      "focus": [
        "المصدر الرسمي الدقيق لتسجيل القهوة العربية في اليونسكو"
      ],
      "gaps": [
        "بالإنجليزية فقط، غير مترجم أو مبسط لقارئ عربي"
      ]
    },
    {
      "site": "saudipedia.com",
      "type": "reference",
      "url": "https://saudipedia.com/en/saudi-coffee",
      "focus": [
        "يوضح الفرق بين القهوة السعودية كاسم محلي والقهوة العربية كتسجيل يونسكو مشترك"
      ],
      "gaps": [
        "موسوعي عام، غير موجه لسؤال اليوم العالمي للقهوة تحديداً"
      ]
    },
    {
      "site": "alriyadh.com",
      "type": "arabic-competitor",
      "url": "https://www.alriyadh.com/1107156",
      "focus": [
        "خبر إدراج القهوة العربية في قائمة التراث الثقافي"
      ],
      "gaps": [
        "خبر قديم دون تحديث لاحق يذكر توسيع 2024 ليشمل الأردن"
      ]
    }
  ],
  "coverageMatrix": [
    {
      "keyword": "متى اليوم العالمي للقهوة {{year}}",
      "whyItMatters": "أوضح صيغة مباشرة للباحث الذي يريد التاريخ الحالي بسرعة."
    },
    {
      "keyword": "لماذا 1 أكتوبر يوم القهوة العالمي",
      "whyItMatters": "نية معرفية شائعة تحتاج شرحاً واضحاً لربط التاريخ بموسم الحصاد."
    },
    {
      "keyword": "منظمة القهوة الدولية",
      "whyItMatters": "الجهة المؤسسة لليوم، وسؤال متكرر عن هوية الجهة المسؤولة."
    },
    {
      "keyword": "القهوة العربية اليونسكو",
      "whyItMatters": "أهم زاوية فخر ثقافي عربي مرتبطة باليوم، وأكثر ما يميز هذه الصفحة عن المنافسين."
    },
    {
      "keyword": "الفرق بين القهوة العربية والقهوة السعودية",
      "whyItMatters": "أكبر نقطة التباس فعلية تخلط فيها أغلب المصادر العربية بين الاسمين."
    },
    {
      "keyword": "من أسس اليوم العالمي للقهوة",
      "whyItMatters": "سؤال تاريخي مباشر يربط اليوم بمنظمة القهوة الدولية وقرار 2014."
    },
    {
      "keyword": "هل القهوة العربية مسجلة في اليونسكو",
      "whyItMatters": "سؤال تأكيدي مباشر يحتاج إجابة قاطعة (نعم) مع تفاصيل دقيقة."
    },
    {
      "keyword": "اليوم العالمي للقهوة {{nextYear}}",
      "whyItMatters": "يخدم الباحث الذي يخطط مسبقاً للعام القادم ويؤكد ثبات التاريخ."
    }
  ],
  "keywordGaps": [
    "ربط واضح ودقيق بين اليوم العالمي للقهوة وتسجيل القهوة العربية في اليونسكو في العام نفسه (2015)",
    "توضيح صريح وأمين للفرق بين القهوة العربية (تسجيل يونسكو مشترك) والقهوة السعودية (اسم محلي)، وهي نقطة يخطئ فيها كثيرون",
    "تحديث معلومة توسيع تسجيل اليونسكو ليشمل الأردن سنة 2024، وهي معلومة حديثة تغيب عن أغلب المصادر العربية",
    "عداد تنازلي حي لموعد 1 أكتوبر بدل الاكتفاء بمقال ثقافي عام يتكرر سنوياً",
    "شرح دقيق لهوية منظمة القهوة الدولية (ICO) ودورها التأسيسي، بدل ذكرها بشكل عابر",
    "ربط اختيار التاريخ (1 أكتوبر) بموسم حصاد القهوة عالمياً بدل تقديمه كتاريخ رمزي فقط",
    "صفحة تخدم زاوية سعودية خاصة (عام القهوة السعودية 2022) دون التقليل من الطابع المشترك للقهوة العربية بين خمس دول",
    "تغطية متوازنة تحترم كل الدول المشاركة في تسجيل اليونسكو (الإمارات، السعودية، عُمان، قطر، الأردن) دون التركيز على دولة واحدة فقط"
  ],
  "unansweredQuestions": [
    "متى اليوم العالمي للقهوة بالضبط؟",
    "لماذا اختير 1 أكتوبر تحديداً؟",
    "من أسس هذا اليوم؟",
    "هل القهوة العربية مسجلة فعلاً في اليونسكو؟",
    "ما الفرق بين القهوة العربية والقهوة السعودية؟",
    "أي دول شاركت في تسجيل القهوة العربية في اليونسكو؟"
  ],
  "differentiationIdeas": [
    "الإجابة المباشرة في أول 100 كلمة عن الموعد، مع ربط فوري بقصة القهوة العربية في اليونسكو، وهو ربط لا تقدمه أغلب الصفحات المنافسة بوضوح",
    "عداد تنازلي حي لتاريخ 1 أكتوبر بدل الاكتفاء بمقال ثقافي عام يتكرر سنوياً بصياغة شبه متطابقة",
    "توضيح دقيق وصريح للفرق بين القهوة العربية (تسجيل يونسكو مشترك بين خمس دول) والقهوة السعودية (اسم محلي)، مصحح لالتباس شائع في المصادر العربية",
    "تحديث حصري نسبياً لتوسيع تسجيل اليونسكو ليشمل الأردن سنة 2024، معلومة لا تزال أغلب المصادر العربية لا تذكرها",
    "ربط اختيار تاريخ 1 أكتوبر بموسم حصاد القهوة عالمياً كسبب حقيقي، بدل تقديمه كتاريخ رمزي فقط",
    "زاوية سعودية إضافية (عام القهوة السعودية 2022) عبر صفحة دولة مخصصة، تخدم أعلى قيمة إعلانية دون التقليل من الطابع المشترك للتراث العربي",
    "الاعتماد المباشر على صفحات اليونسكو الرسمية كمصدر أساسي، بدل الاكتفاء بمصادر إخبارية ثانوية منقولة"
  ],
  "factSources": [
    {
      "label": "ويكيبيديا العربية — اليوم العالمي للقهوة",
      "url": "https://ar.wikipedia.org/wiki/اليوم_العالمي_للقهوة"
    },
    {
      "label": "اليونسكو — القهوة العربية رمز الكرم (قرار توسيع التسجيل)",
      "url": "https://ich.unesco.org/en/decisions/19.COM/7.B.55"
    },
    {
      "label": "منظمة اليونسكو — صفحة تسجيل القهوة العربية رمز الكرم",
      "url": "https://ich.unesco.org/en/RL/arabic-coffee-a-symbol-of-generosity-01074"
    },
    {
      "label": "سعوديبيديا — التراث الثقافي غير المادي السعودي في اليونسكو",
      "url": "https://saudipedia.com/en/saudi-coffee"
    }
  ],
  "notes": "تم التحقق بعناية من نقطة كانت غير دقيقة في التخطيط الأولي: الأصل خطط لوصف القهوة السعودية بأنها مُدرجة في اليونسكو، لكن التحقق المباشر من صفحة اليونسكو الرسمية (ich.unesco.org) أظهر أن الاسم الرسمي المسجل هو (القهوة العربية، رمز الكرم) وليس (القهوة السعودية)، وأنه تسجيل مشترك بين الإمارات والسعودية وعُمان وقطر منذ 2015، ووُسّع في ديسمبر 2024 (قرار 19.COM 7.B.55) ليشمل الأردن أيضاً. القهوة السعودية اسم محلي ترويجي بدأ فعلياً مع مبادرة عام القهوة السعودية 2022، وهو منفصل عن تسجيل اليونسكو وليس بديلاً عنه. هذا التصحيح أصبح هو المحتوى الأساسي المميز للصفحة بدل تكرار الخطأ الشائع في مصادر عربية أخرى."
}
