{
  "slug": "social-security-saudi",
  "locale": "ar",
  "capturedAt": "2026-05-01T20:21:24.169Z",
  "primaryQueries": [
    "متى ينزل الضمان الاجتماعي المطور",
    "كم باقي على الضمان الاجتماعي المطور",
    "موعد الضمان الاجتماعي المطور {{year}}",
    "الأهلية 27 الضمان الاجتماعي",
    "صرف الضمان الاجتماعي 1 ميلادي",
    "متى ينزل الضمان الاجتماعي المطور {{year}}",
    "كم باقي على الضمان الاجتماعي المطور {{year}}",
    "الضمان الاجتماعي المطور السعودية",
    "الضمان الاجتماعي المطور {{year}}",
    "تاريخ الضمان الاجتماعي المطور {{year}}",
    "متى الضمان الاجتماعي المطور {{nextYear}}",
    "الضمان الاجتماعي المطور العد التنازلي"
  ],
  "competitors": [
    {
      "site": "hrsd.gov.sa",
      "type": "official",
      "url": "https://www.hrsd.gov.sa/media-center/news/%D9%85%D8%B9%D8%A7%D9%8A%D9%8A%D8%B1%C2%A0%D9%88%D8%AE%D8%B7%D9%88%D8%A7%D8%AA-%D9%84%D9%84%D8%A3%D9%87%D9%84%D9%8A%D8%A9",
      "focus": [
        "يوم 27 لإعلان الأهلية",
        "اليوم الأول للصرف",
        "آلية الاعتراض",
        "المستندات المطلوبة"
      ],
      "gaps": [
        "ليست صفحة بحثية SEO مبنية على عبارة متى ينزل الضمان",
        "لا تعرض عداداً زمنياً مباشراً",
        "تتطلب تنقلاً بين أكثر من صفحة لفهم الصورة كاملة"
      ]
    },
    {
      "site": "mountada.net",
      "type": "news",
      "url": "https://mountada.net/article/when-will-the-new-upgraded-social-security-come-/",
      "focus": [
        "عنوان متى ينزل الضمان",
        "جواب سريع عن الدفعة الحالية",
        "جدول مختصر"
      ],
      "gaps": [
        "تقادم سريع",
        "ضعف الربط بالنظام المطور نفسه",
        "قلة التفريق بين الأهلية والصرف والاعتراض"
      ]
    },
    {
      "site": "المواقع الخدمية الإخبارية",
      "type": "countdown",
      "focus": [
        "كم باقي على الضمان",
        "خبر شهري",
        "التاريخ الحالي"
      ],
      "gaps": [
        "تكرار محتوى متشابه",
        "ضعف الشرح النظامي",
        "إهمال يوم 27 ودور الأهلية"
      ]
    },
    {
      "site": "prod.hrsd.gov.sa",
      "type": "reference",
      "url": "https://prod.hrsd.gov.sa/si/node/1170297",
      "focus": [
        "التاريخ الرسمي لـ الضمان الاجتماعي المطور",
        "سياق الضمان الاجتماعي المطور"
      ],
      "gaps": [
        "غالباً لا تقدم صفحة عربية تجمع الموعد والشرح والعد التنازلي في مكان واحد."
      ]
    },
    {
      "site": "hrsd.gov.sa",
      "type": "reference",
      "url": "https://www.hrsd.gov.sa/node/69888",
      "focus": [
        "التاريخ الرسمي لـ الضمان الاجتماعي المطور",
        "سياق الضمان الاجتماعي المطور"
      ],
      "gaps": [
        "غالباً لا تقدم صفحة عربية تجمع الموعد والشرح والعد التنازلي في مكان واحد."
      ]
    }
  ],
  "coverageMatrix": [
    {
      "keyword": "متى ينزل الضمان الاجتماعي المطور",
      "whyItMatters": "الاستعلام الشهري الأوضح بنية مالية مباشرة."
    },
    {
      "keyword": "كم باقي على الضمان الاجتماعي المطور",
      "whyItMatters": "يتطابق مع بنية العداد ويزيد قيمة الصفحة قبل موعد الصرف."
    },
    {
      "keyword": "الأهلية 27 الضمان الاجتماعي",
      "whyItMatters": "يلتقط الفجوة الأهم بين الخبر الشهري والقاعدة الرسمية."
    },
    {
      "keyword": "صرف الضمان الاجتماعي 1 ميلادي",
      "whyItMatters": "صيغة عملية يكتبها المستخدم عندما يريد تثبيت القاعدة لا متابعة خبر قديم."
    },
    {
      "keyword": "موعد الضمان الاجتماعي المطور {{year}}",
      "whyItMatters": "نية مباشرة لمعرفة التاريخ الحالي أو أقرب موعد للمناسبة بطريقة سريعة وواضحة."
    },
    {
      "keyword": "متى ينزل الضمان الاجتماعي المطور {{year}}",
      "whyItMatters": "نية مباشرة لمعرفة التاريخ الحالي أو أقرب موعد للمناسبة بطريقة سريعة وواضحة."
    },
    {
      "keyword": "كم باقي على الضمان الاجتماعي المطور {{year}}",
      "whyItMatters": "نية عد تنازلي مباشرة تناسب الباحث الذي يريد معرفة المدة المتبقية بسرعة."
    },
    {
      "keyword": "الضمان الاجتماعي المطور السعودية",
      "whyItMatters": "صيغة بحث داعمة تزيد من تغطية الصفحة لطرق البحث العربية المختلفة حول المناسبة."
    }
  ],
  "keywordGaps": [
    "التفريق الواضح بين يوم الأهلية ويوم الصرف",
    "شرح متى يبدأ الصرف بعد قبول الطلب لأول مرة",
    "ربط النظام المطور بخلفيته الرسمية منذ 20 نوفمبر 2021",
    "جواب عربي مباشر يوضح معنى الضمان الاجتماعي المطور وموعده في صفحة واحدة.",
    "شرح سبب أهمية الضمان الاجتماعي المطور ولماذا يرتفع البحث عنه عند اقتراب الموعد.",
    "تغطية الأسئلة العملية التي يطرحها القارئ قبل الضمان الاجتماعي المطور أو أثناءه.",
    "صياغة أوضح حول التاريخ الحالي والسنوات القادمة بدل الاكتفاء باسم المناسبة فقط.",
    "دمج العد التنازلي مع الشرح والسياق بدل صفحة موعد قصيرة وضعيفة."
  ],
  "unansweredQuestions": [
    "لماذا يهمني يوم 27 ميلادي في الضمان المطور؟",
    "متى يبدأ الصرف بعد قبول الطلب لأول مرة؟",
    "ما الفرق بين الاعتراض على الأهلية والشكوى المالية؟",
    "متى ينزل الضمان الاجتماعي المطور {{year}}؟",
    "كم باقي على الضمان الاجتماعي المطور؟",
    "ما هو الضمان الاجتماعي المطور؟",
    "كيف أعرف أهلية الضمان الاجتماعي المطور؟",
    "متى الضمان الاجتماعي المطور {{nextYear}}؟"
  ],
  "differentiationIdeas": [
    "جمع العداد الشهري مع القاعدة الرسمية للأهلية والصرف في مرجع واحد",
    "ربط الاستعلام الشعبي بالنص الرسمي للوزارة لا بخبر شهري عابر",
    "تحويل الصفحة إلى مرجع شهري دائم بدلاً من إعادة كتابة خبر جديد كل شهر",
    "جواب مباشر عن موعد الضمان الاجتماعي المطور في بداية الصفحة قبل أي شرح إضافي.",
    "محتوى عربي يشرح المعنى والسياق بدلاً من الاكتفاء بعداد أو تاريخ مختصر.",
    "أسئلة شائعة عملية تساعد القارئ على فهم الضمان الاجتماعي المطور والتصرف بناءً عليه."
  ],
  "factSources": [
    {
      "label": "وزارة الموارد البشرية: شروط الاستحقاق في نظام الضمان الاجتماعي المطور",
      "url": "https://prod.hrsd.gov.sa/si/node/1170297"
    },
    {
      "label": "وزارة الموارد البشرية: نظام الضمان الاجتماعي المطور",
      "url": "https://www.hrsd.gov.sa/node/69888"
    },
    {
      "label": "وزارة الموارد البشرية: تبدأ تفعيل نظام الضمان الاجتماعي المطور",
      "url": "https://www.hrsd.gov.sa/media-center/news/950786"
    },
    {
      "label": "نظام الضمان الاجتماعي",
      "url": "https://www.hrsd.gov.sa/en/node/841045"
    },
    {
      "label": "hrsd.gov.sa",
      "url": "https://www.hrsd.gov.sa/media-center/news/%D9%85%D8%B9%D8%A7%D9%8A%D9%8A%D8%B1%C2%A0%D9%88%D8%AE%D8%B7%D9%88%D8%A7%D8%AA-%D9%84%D9%84%D8%A3%D9%87%D9%84%D9%8A%D8%A9"
    },
    {
      "label": "mountada.net",
      "url": "https://mountada.net/article/when-will-the-new-upgraded-social-security-come-/"
    }
  ],
  "notes": "أكبر فرصة في هذه الصفحة هي بناء مرجع شهري دائم يشرح اليومين الحاسمين 27 و1 ميلادي بدلاً من الاكتفاء بخبر دفعة الشهر الحالي، لأن الطلب البحثي يتكرر يومياً وبنية مالية واضحة."
}
