{
  "slug": "isra-miraj",
  "locale": "ar",
  "capturedAt": "2026-06-01T00:00:00.000Z",
  "primaryQueries": [
    "متى ليلة الإسراء والمعراج {{year}}",
    "كم باقي على ليلة الإسراء والمعراج {{year}}",
    "27 رجب {{year}}",
    "هل 27 رجب ثابت",
    "ما الذي فرض في المعراج",
    "هل يجوز صيام 27 رجب",
    "حكم الاحتفال بليلة الإسراء والمعراج",
    "هل الإسراء والمعراج إجازة",
    "قصة الإسراء والمعراج",
    "ليلة الإسراء والمعراج {{nextYear}}"
  ],
  "competitors": [
    {
      "site": "calendarz.com",
      "type": "arabic",
      "url": "https://www.calendarz.com/ar/when-is/muslim-holidays/lailat-al-miraj/2025",
      "focus": [
        "التاريخ المتداول",
        "العداد",
        "شرح مختصر للقصة"
      ],
      "gaps": [
        "سنة محددة",
        "لا يشرح التحفظ العلمي في تعيين 27 رجب",
        "ضعيف في مسألة العبادات المخصوصة"
      ]
    },
    {
      "site": "islamqa.info",
      "type": "arabic-reference",
      "url": "https://islamqa.info/ar/answers/60288",
      "focus": [
        "ثبوت أصل الحدث",
        "عدم ثبوت تعيين الليلة على وجه الجزم",
        "عدم تخصيصها بعبادة أو احتفال"
      ],
      "gaps": [
        "ليست صفحة موعد أو عد تنازلي",
        "لا تخدم نية التاريخ والإجازة مباشرة"
      ]
    },
    {
      "site": "islamweb.net",
      "type": "arabic-reference",
      "url": "https://islamweb.net/ar/fatwa/98501/%D9%84%D9%85-%D9%8A%D8%AB%D8%A8%D8%AA-%D9%81%D8%B6%D9%84-%D8%AE%D8%A7%D8%B5-%D9%84%D8%B5%D9%8A%D8%A7%D9%85-27-%D8%B1%D8%AC%D8%A8-%D8%A3%D9%88-15-%D8%B4%D8%B9%D8%A8%D8%A7%D9%86",
      "focus": [
        "عدم ثبوت فضل خاص لصيام 27 رجب",
        "التفريق بين النافلة العامة والتخصيص"
      ],
      "gaps": [
        "لا يشرح القصة أو الموعد",
        "ليس متمحوراً حول نية العد التنازلي"
      ]
    },
    {
      "site": "timeanddate.com",
      "type": "english",
      "url": "https://www.timeanddate.com/holidays/us/isra-miraj",
      "focus": [
        "التاريخ المتداول",
        "تغير الموعد سنوياً",
        "وضع العطلة في بعض الدول"
      ],
      "gaps": [
        "لا يناقش مسألة ثبوت 27 رجب",
        "يتعامل مع المناسبة كتقويم أكثر من كونها مادة تفسيرية"
      ]
    },
    {
      "site": "dar-alifta.org",
      "type": "english-reference",
      "url": "https://dar-alifta.org/en/article/details/1871/the-miracle-of-the-night-journey-and-heavenly-ascension-of-prophet-muhammad",
      "focus": [
        "المعنى العام للمناسبة",
        "ربطها بليلة 27 رجب في العمل العام",
        "الشرح الديني المختصر"
      ],
      "gaps": [
        "لا تخاطب نية الموعد وحدها",
        "لا تعطي زاوية نقدية حول الجزم التاريخي"
      ]
    },
    {
      "site": "icalendars.net",
      "type": "english",
      "url": "https://icalendars.net/religion/islamism/lailat-al-miraj",
      "focus": [
        "التاريخ المتداول",
        "تعريف المناسبة",
        "التحرك السنوي في التقويم"
      ],
      "gaps": [
        "محتوى عام وخفيف",
        "لا يميز بين الاشتهار والثبوت العلمي"
      ]
    }
  ],
  "coverageMatrix": [
    {
      "keyword": "متى ليلة الإسراء والمعراج {{year}}",
      "whyItMatters": "المدخل الزمني الرئيسي للصفحة."
    },
    {
      "keyword": "27 رجب {{year}}",
      "whyItMatters": "صيغة البحث الشعبية الأقوى حول المناسبة."
    },
    {
      "keyword": "هل 27 رجب ثابت",
      "whyItMatters": "فجوة علمية لا تغطيها معظم الصفحات المنافسة بوضوح."
    },
    {
      "keyword": "هل يجوز صيام 27 رجب",
      "whyItMatters": "سؤال عملي متكرر يرتبط بالموسم مباشرة."
    },
    {
      "keyword": "ما الذي فرض في المعراج",
      "whyItMatters": "أكثر سؤال تعليمي مرتبط بالقصة."
    },
    {
      "keyword": "هل الإسراء والمعراج إجازة",
      "whyItMatters": "يغطي نية عملية تختلف باختلاف البلد."
    },
    {
      "keyword": "قصة الإسراء والمعراج",
      "whyItMatters": "يضبط الحد الأدنى التفسيري الذي يتوقعه القارئ."
    },
    {
      "keyword": "كم باقي على ليلة الإسراء والمعراج {{year}}",
      "whyItMatters": "يرتبط مباشرة بنموذج صفحة المناسبة."
    }
  ],
  "arabicCompetitors": [
    {
      "url": "https://www.calendarz.com/ar/when-is/muslim-holidays/lailat-al-miraj/2025",
      "title": "الإسراء والمعراج | ما هو موعد الإسراء والمعراج؟ - كاليندرز",
      "metaDescription": "التاريخ والعداد وشرح سريع للرحلة.",
      "h1": "الإسراء والمعراج",
      "headings": [
        "ما هو موعد الإسراء والمعراج",
        "ما هو الإسراء والمعراج",
        "التاريخ في السنوات القادمة"
      ],
      "bodyWordCount": 260,
      "faqCount": 0,
      "tableCount": 1,
      "confidence": "medium",
      "strengths": [
        "قوي في نية الموعد",
        "يعطي صيغة التقويم التي يبحث عنها المستخدم"
      ],
      "weaknesses": [
        "سطحي",
        "لا يوضح الفرق بين التاريخ المتداول والثبوت العلمي"
      ]
    },
    {
      "url": "https://islamqa.info/ar/answers/60288",
      "title": "ما حكم الاحتفال بليلة الإسراء والمعراج؟ - الإسلام سؤال وجواب",
      "metaDescription": "جواب علمي عن ثبوت الليلة وحكم الاحتفال بها.",
      "h1": "ما حكم الاحتفال بليلة الإسراء والمعراج؟",
      "headings": [
        "الإسراء والمعراج من آيات الله العظيمة",
        "هل صح شيء في ليلة الإسراء والمعراج",
        "هل يجوز الاحتفال بليلة الإسراء والمعراج"
      ],
      "bodyWordCount": 700,
      "faqCount": 0,
      "tableCount": 0,
      "confidence": "high",
      "strengths": [
        "أقوى مصدر في نفي الجزم بليلة 27 رجب",
        "يصوب المحتوى الموسمي الضعيف"
      ],
      "weaknesses": [
        "لا يقدم التاريخ المتداول أو العد التنازلي"
      ]
    },
    {
      "url": "https://islamweb.net/ar/fatwa/98501/%D9%84%D9%85-%D9%8A%D8%AB%D8%A8%D8%AA-%D9%81%D8%B6%D9%84-%D8%AE%D8%A7%D8%B5-%D9%84%D8%B5%D9%8A%D8%A7%D9%85-27-%D8%B1%D8%AC%D8%A8-%D8%A3%D9%88-15-%D8%B4%D8%B9%D8%A8%D8%A7%D9%86",
      "title": "لم يثبت فضل خاص لصيام 27 رجب أو 15 شعبان - إسلام ويب",
      "metaDescription": "جواب فقهي عن صيام 27 رجب وتخصيصه.",
      "h1": "لم يثبت فضل خاص لصيام 27 رجب أو 15 شعبان",
      "headings": [
        "السؤال",
        "خلاصة الفتوى",
        "الإجابة"
      ],
      "bodyWordCount": 280,
      "faqCount": 0,
      "tableCount": 0,
      "confidence": "high",
      "strengths": [
        "مباشر في مسألة الصيام والتخصيص",
        "يسد فجوة شائعة في البحث"
      ],
      "weaknesses": [
        "ليس صفحة تعريف أو موعد"
      ]
    }
  ],
  "englishCompetitors": [
    {
      "url": "https://www.timeanddate.com/holidays/us/isra-miraj",
      "title": "Isra and Mi'raj in the United States | Timeanddate",
      "metaDescription": "الموعد والتغير السنوي ووضع المناسبة كعطلة أو لا.",
      "h1": "Isra and Mi'raj in the United States",
      "headings": [
        "When Is Isra and Mi'raj",
        "Is Isra and Mi'raj a Public Holiday",
        "Background"
      ],
      "bodyWordCount": 500,
      "faqCount": 0,
      "tableCount": 1,
      "confidence": "high",
      "strengths": [
        "مفيد في التاريخ المتداول والتحرك السنوي",
        "يخدم سؤال الإجازة بوضوح"
      ],
      "weaknesses": [
        "تقويمي أكثر من كونه تفسيرياً",
        "لا يناقش مسألة الجزم بتاريخ 27 رجب"
      ]
    },
    {
      "url": "https://dar-alifta.org/en/article/details/1871/the-miracle-of-the-night-journey-and-heavenly-ascension-of-prophet-muhammad",
      "title": "The Miracle of the Night Journey and Heavenly Ascension of Prophet Muhammad",
      "metaDescription": "شرح ديني مختصر لمعنى المناسبة وارتباطها بالعمل العام.",
      "h1": "The Miracle of the Night Journey and Heavenly Ascension of Prophet Muhammad",
      "headings": [
        "Night Journey",
        "Ascension",
        "Commemoration"
      ],
      "bodyWordCount": 650,
      "faqCount": 0,
      "tableCount": 0,
      "confidence": "high",
      "strengths": [
        "يشرح الحدث بإيجاز جيد",
        "يعكس طريقة تداوله في المؤسسات الدينية"
      ],
      "weaknesses": [
        "لا يحذر بما يكفي من الجزم التاريخي",
        "ليس موجهاً لنية العد التنازلي"
      ]
    },
    {
      "url": "https://icalendars.net/religion/islamism/lailat-al-miraj",
      "title": "Lailat al Miraj - Dates and origins",
      "metaDescription": "تعريف عام بالمناسبة وتواريخها.",
      "h1": "Lailat al Miraj",
      "headings": [
        "Dates",
        "Origins",
        "Observance"
      ],
      "bodyWordCount": 320,
      "faqCount": 0,
      "tableCount": 1,
      "confidence": "medium",
      "strengths": [
        "مفيد كتقويم مقارن",
        "واضح في فكرة التحرك السنوي"
      ],
      "weaknesses": [
        "خفيف جداً",
        "يفتقد العمق والدقة الحديثية"
      ]
    }
  ],
  "keywordGaps": [
    "الجواب المبكر عن مسألة ثبوت 27 رجب",
    "التفريق بين الحدث الثابت والتاريخ المتداول",
    "شرح سريع لسؤال فرض الصلاة",
    "تصحيح مسألة صيام 27 رجب",
    "معالجة سؤال الإجازة من دون تعميم مضلل",
    "بنية FAQ تحل الالتباس لا تعيده",
    "أول 100 كلمة تجيب عن سؤال الموعد والمعنى معاً",
    "مصادر أوضح للقضايا الحساسة من الصفحات الخبرية الموسمية"
  ],
  "unansweredQuestions": [
    "هل ثبتت ليلة الإسراء والمعراج في 27 رجب؟",
    "هل يجوز صيام 27 رجب؟",
    "ما الذي فرض في المعراج؟",
    "هل الإسراء والمعراج إجازة؟",
    "متى ليلة الإسراء والمعراج {{year}}؟",
    "كم باقي على ليلة الإسراء والمعراج؟"
  ],
  "differentiationIdeas": [
    "بناء الصفحة حول التاريخ المتداول مع التحفظ العلمي الواضح",
    "تحويل الصفحة من عداد أو قصة طويلة إلى مرجع عربي متوازن",
    "استخدام المصادر الفقهية لتصحيح أكثر الأخطاء انتشاراً",
    "ربط سؤال الموعد بسؤال المعنى وسؤال ما لا يثبت"
  ],
  "factSources": [
    {
      "label": "القرآن الكريم - سورة الإسراء 17:1",
      "url": "https://quran.com/17/1"
    },
    {
      "label": "الإسلام سؤال وجواب: ما حكم الاحتفال بليلة الإسراء والمعراج؟",
      "url": "https://islamqa.info/ar/answers/60288"
    },
    {
      "label": "إسلام ويب: لم يثبت فضل خاص لصيام 27 رجب أو 15 شعبان",
      "url": "https://islamweb.net/ar/fatwa/98501/%D9%84%D9%85-%D9%8A%D8%AB%D8%A8%D8%AA-%D9%81%D8%B6%D9%84-%D8%AE%D8%A7%D8%B5-%D9%84%D8%B5%D9%8A%D8%A7%D9%85-27-%D8%B1%D8%AC%D8%A8-%D8%A3%D9%88-15-%D8%B4%D8%B9%D8%A8%D8%A7%D9%86"
    }
  ],
  "notes": "تم استبعاد الصفحات الخبرية والمحتوى الموسمي الذي يقدم 27 رجب على أنه يقين بلا تحفظ، أو يضيف عبادات خاصة بلا مصادر قوية. الهدف هنا أن تكون الصفحة أفضل من نتائج الموعد الضعيفة ومن المقالات التي تطيل القصة وتترك أهم سؤالين بلا جواب: هل التاريخ ثابت؟ وهل لهذا اليوم عبادة مخصوصة؟"
}
