{
  "slug": "recapture-of-riyadh",
  "locale": "ar",
  "capturedAt": "2026-07-13T05:51:50.098Z",
  "primaryQueries": [
    "متى ذكرى استرداد الرياض {{year}}",
    "استرداد الرياض",
    "اقتحام قصر المصمك",
    "عجلان بن محمد",
    "الدولة السعودية الثالثة",
    "خوخة المصمك",
    "كم باقي على ذكرى استرداد الرياض {{year}}",
    "ذكرى استرداد الرياض {{nextYear}}",
    "من قتل عجلان بن محمد في المصمك",
    "كم كان عدد رجال عبدالعزيز في اقتحام المصمك"
  ],
  "competitors": [
    {
      "site": "ar.wikipedia.org",
      "type": "reference",
      "url": "https://ar.wikipedia.org/wiki/معركة_الرياض_(1902)",
      "focus": [
        "مرجع موسوعي شامل عن معركة استرداد الرياض 1902"
      ],
      "gaps": [
        "مرجع عام دون عداد تنازلي أو تمييز صريح عن يوم التأسيس واليوم الوطني"
      ]
    },
    {
      "site": "saudipedia.com",
      "type": "reference",
      "url": "https://saudipedia.com/article/15463",
      "focus": [
        "مرجع سعودي رسمي النبرة بتفاصيل دقيقة عن الحدث"
      ],
      "gaps": [
        "لا يوجد تفاعل أو عداد، ولا ربط بمناسبات سعودية أخرى مشابهة الاسم"
      ]
    },
    {
      "site": "sabq.org",
      "type": "arabic-competitor",
      "url": "https://sabq.org/saudia/bsgtkc27q3",
      "focus": [
        "أفضل سرد قصصي، يعيد رواية الملك عبدالعزيز نفسه بصيغة المتكلم"
      ],
      "gaps": [
        "مقال استرجاعي موسمي واحد، دون بنية سنوية متكررة أو عداد تنازلي"
      ]
    },
    {
      "site": "roadtoriyadh.com",
      "type": "arabic-competitor",
      "url": "https://roadtoriyadh.com",
      "focus": [
        "موقع/مشروع وثائقي مصغر مخصص للحدث"
      ],
      "gaps": [
        "محتوى ثابت دون عداد حي، ودون تمييز واضح عن يوم التأسيس/اليوم الوطني"
      ]
    },
    {
      "site": "en.wikipedia.org",
      "type": "english-competitor",
      "url": "https://en.wikipedia.org/wiki/Battle_of_Riyadh",
      "focus": [
        "مرجع إنجليزي بمعلومات جيدة"
      ],
      "gaps": [
        "يحتوي تضارباً داخلياً في التاريخ (13 مقابل 15/16 يناير)، ولا عداد تنازلي"
      ]
    }
  ],
  "coverageMatrix": [
    {
      "keyword": "متى ذكرى استرداد الرياض {{year}}",
      "whyItMatters": "أوضح صيغة بحث مباشرة عن الموعد السنوي."
    },
    {
      "keyword": "اقتحام قصر المصمك",
      "whyItMatters": "الاسم الشعبي الأكثر تداولاً للحدث نفسه."
    },
    {
      "keyword": "من قتل عجلان بن محمد في المصمك",
      "whyItMatters": "سؤال شائع يحتاج توضيحاً صريحاً مع الإقرار بتضارب الروايات."
    },
    {
      "keyword": "كم كان عدد رجال عبدالعزيز في اقتحام المصمك",
      "whyItMatters": "تفصيل رقمي متداول شعبياً (40 رجلاً) يحتاج توضيحاً أميناً لتضارب المصادر."
    },
    {
      "keyword": "هل استرداد الرياض هو نفسه يوم التأسيس",
      "whyItMatters": "يميز الصفحة عن مناسبتين سعوديتين أخريين حيّتين على الموقع."
    },
    {
      "keyword": "قصة أثر الرمح في باب قصر المصمك",
      "whyItMatters": "تفصيل بصري ونادر يميز المحتوى عن المراجع الجافة."
    },
    {
      "keyword": "كم باقي على ذكرى استرداد الرياض {{year}}",
      "whyItMatters": "صيغة عد تنازلي مباشرة."
    },
    {
      "keyword": "ذكرى استرداد الرياض {{nextYear}}",
      "whyItMatters": "يخدم من يخطط مسبقاً لمحتوى أو نشاط."
    }
  ],
  "keywordGaps": [
    "لا توجد صفحة عربية بعداد تنازلي حي لهذه الذكرى — كل المحتوى الموجود موسوعي أو إخباري موسمي",
    "تمييز صريح عن يوم التأسيس (1727، الدولة الأولى) واليوم الوطني (1932) — نقطة خلط شائعة لم تُعالج بوضوح في أي مصدر",
    "توضيح أمين لتضارب المصادر حول عدد الرجال (40 مقابل 60-68) بدل اختيار رقم واحد كحقيقة مطلقة",
    "توضيح من قتل عجلان فعلياً (عبدالله بن جلوي في أغلب الروايات العربية) دون حسم زائف",
    "استغلال تفصيل أثر الرمح في باب المصمك (لا يزال قائماً في المتحف) كعنصر بصري ومثير",
    "ربط الصفحة بعنقود الأحداث التاريخية السعودية والإسلامية الحية على الموقع (saudi-founding-day, saudi-national-day, badr-day, fath-makkah)",
    "الحفاظ على نبرة تاريخية محايدة دون أي خوض في جدل سياسي معاصر",
    "استخدام countryScope: none وcategory: national كحدث سعودي وحيد بتاريخ ميلادي ثابت"
  ],
  "unansweredQuestions": [
    "متى هذا اليوم بالضبط؟",
    "ماذا حدث فعلياً في استرداد الرياض؟",
    "من قتل عجلان بن محمد؟",
    "كم كان عدد رجال عبدالعزيز؟",
    "هل هو نفسه يوم التأسيس أو اليوم الوطني؟",
    "لماذا يشتهر أثر الرمح في باب المصمك؟"
  ],
  "differentiationIdeas": [
    "الإجابة المباشرة في أول جملة عن الموعد (15 يناير) والعد التنازلي، قبل أي سرد تاريخي",
    "سرد قصصي حي لتفاصيل الاقتحام (التسلل، انتحال هوية الرسول، المواجهة عند الباب) بدل جفاف المرجع الموسوعي",
    "توضيح أمين لتضارب المصادر (العدد، القاتل الفعلي) بدل تقديم رواية واحدة كحقيقة مطلقة",
    "تمييز ثلاثي واضح بين استرداد الرياض (1902) ويوم التأسيس (1727) واليوم الوطني (1932) — فجوة حقيقية يستغلها الموقع وحده",
    "الربط بعنقود الأحداث التاريخية السعودية/الإسلامية الحية على الموقع"
  ],
  "factSources": [
    {
      "label": "ويكيبيديا العربية — معركة الرياض (1902)",
      "url": "https://ar.wikipedia.org/wiki/معركة_الرياض_(1902)"
    },
    {
      "label": "Saudipedia — استرداد الرياض",
      "url": "https://saudipedia.com/article/15463"
    },
    {
      "label": "سبق — رواية الملك عبدالعزيز لاقتحام المصمك",
      "url": "https://sabq.org/saudia/bsgtkc27q3"
    },
    {
      "label": "Wikipedia (EN) — Battle of Riyadh",
      "url": "https://en.wikipedia.org/wiki/Battle_of_Riyadh"
    }
  ],
  "notes": "تم التحقق عبر بحث ويب مباشر (2026-07-13) من عدة مصادر مستقلة: التاريخ الميلادي المعتمد عربياً هو 15 يناير 1902 (5 شوال 1319هـ)، رغم اختلاف المصادر الإنجليزية بين 13/15/16 يناير — تم اعتماد الإجماع العربي. عدد رجال عبدالعزيز متضارب بين المصادر (40 وفق روايته الشخصية، حتى 68 في مصادر أخرى) — تم عرض ذلك بصدق دون حسم رقم واحد. قاتل عجلان بن محمد الفعلي غير محسوم بيقين مطلق بين المصادر (عبدالله بن جلوي في أغلب الروايات العربية) — تم عرضه بصيغة 'بحسب أغلب الروايات' بدل الجزم. تفصيل أثر الرمح في باب المصمك مؤكد ومتداول كعنصر بصري حي في القصة الشعبية. تم تمييز الحدث بوضوح عن saudi-founding-day (1727) وsaudi-national-day (1932) الحيّين على الموقع."
}
