{
  "slug": "takaful-karama-egypt",
  "locale": "ar",
  "capturedAt": "2026-05-01T20:21:24.176Z",
  "primaryQueries": [
    "متى ينزل تكافل وكرامة",
    "كم باقي على تكافل وكرامة",
    "موعد تكافل وكرامة {{year}}",
    "تكافل وكرامة يوم 15",
    "صرف تكافل وكرامة هذا الشهر",
    "متى ينزل تكافل وكرامة {{year}}",
    "كم باقي على تكافل وكرامة {{year}}",
    "وزارة التضامن تكافل وكرامة",
    "تكافل وكرامة (مصر) {{year}}",
    "كم باقي على تكافل وكرامة (مصر) {{year}}",
    "موعد تكافل وكرامة (مصر) {{year}}",
    "تاريخ تكافل وكرامة (مصر) {{year}}"
  ],
  "competitors": [
    {
      "site": "moss.gov.eg",
      "type": "official",
      "url": "https://www.moss.gov.eg/ar-eg/Pages/news-details.aspx?nid=4637",
      "focus": [
        "موعد بدء الصرف",
        "القنوات الرسمية",
        "الأرقام الشهرية للمستفيدين"
      ],
      "gaps": [
        "البيانات متفرقة على أخبار شهرية متعددة",
        "لا توجد صفحة عداد مباشرة",
        "لا تجمع FAQ الخدمية في صفحة ثابتة"
      ]
    },
    {
      "site": "اليوتيوب والأخبار الخدمية",
      "type": "news",
      "focus": [
        "العناوين السريعة",
        "الشائعات عن الزيادات",
        "موعد الشهر الحالي"
      ],
      "gaps": [
        "ضجيج مرتفع",
        "ضعف التوثيق",
        "اختلاط خبر الزيادة بموعد الصرف"
      ]
    },
    {
      "site": "صفحات العد التنازلي العربية",
      "type": "countdown",
      "focus": [
        "كم باقي",
        "التاريخ المنتظر",
        "العداد السريع"
      ],
      "gaps": [
        "لا تسند الموعد إلى بيانات الوزارة",
        "لا تشرح قنوات الصرف",
        "تغيب عنها أسئلة الزيادة والموعد"
      ]
    },
    {
      "site": "moss.gov.eg",
      "type": "reference",
      "url": "https://www.moss.gov.eg/Sites/MOSA/ar-eg/Pages/news-details.aspx?nid=3804",
      "focus": [
        "التاريخ الرسمي لـ تكافل وكرامة (مصر)",
        "سياق تكافل وكرامة (مصر)"
      ],
      "gaps": [
        "غالباً لا تقدم صفحة عربية تجمع الموعد والشرح والعد التنازلي في مكان واحد."
      ]
    }
  ],
  "coverageMatrix": [
    {
      "keyword": "متى ينزل تكافل وكرامة {{year}}",
      "whyItMatters": "أعلى نية مباشرة لدى المستفيد الشهري."
    },
    {
      "keyword": "كم باقي على تكافل وكرامة {{year}}",
      "whyItMatters": "صيغة عداد قوية ومتكررة في البحث."
    },
    {
      "keyword": "تكافل وكرامة يوم 15",
      "whyItMatters": "تثبت النمط الشهري الأكثر حضوراً في البيانات الرسمية."
    },
    {
      "keyword": "كيف أصرف تكافل وكرامة",
      "whyItMatters": "سؤال عملي يسند الصفحة بعد السؤال الزمني المباشر."
    },
    {
      "keyword": "متى ينزل تكافل وكرامة",
      "whyItMatters": "نية مباشرة لمعرفة التاريخ الحالي أو أقرب موعد للمناسبة بطريقة سريعة وواضحة."
    },
    {
      "keyword": "كم باقي على تكافل وكرامة",
      "whyItMatters": "نية عد تنازلي مباشرة تناسب الباحث الذي يريد معرفة المدة المتبقية بسرعة."
    },
    {
      "keyword": "موعد تكافل وكرامة {{year}}",
      "whyItMatters": "نية مباشرة لمعرفة التاريخ الحالي أو أقرب موعد للمناسبة بطريقة سريعة وواضحة."
    },
    {
      "keyword": "صرف تكافل وكرامة هذا الشهر",
      "whyItMatters": "صيغة بحث داعمة تزيد من تغطية الصفحة لطرق البحث العربية المختلفة حول المناسبة."
    }
  ],
  "keywordGaps": [
    "فصل موعد الصرف عن أخبار الزيادة",
    "ربط النمط الشهري ببيانات الوزارة الرسمية",
    "توضيح قنوات الصرف في الصفحة نفسها",
    "جواب عربي مباشر يوضح معنى تكافل وكرامة (مصر) وموعده في صفحة واحدة.",
    "شرح سبب أهمية تكافل وكرامة (مصر) ولماذا يرتفع البحث عنه عند اقتراب الموعد.",
    "تغطية الأسئلة العملية التي يطرحها القارئ قبل تكافل وكرامة (مصر) أو أثناءه.",
    "صياغة أوضح حول التاريخ الحالي والسنوات القادمة بدل الاكتفاء باسم المناسبة فقط.",
    "دمج العد التنازلي مع الشرح والسياق بدل صفحة موعد قصيرة وضعيفة."
  ],
  "unansweredQuestions": [
    "هل تكافل وكرامة ينزل يوم 15 دائماً؟",
    "كيف أصرف تكافل وكرامة هذا الشهر؟",
    "ما الفرق بين خبر الزيادة وموعد الصرف؟",
    "متى ينزل تكافل وكرامة {{year}}؟",
    "كم باقي على تكافل وكرامة؟",
    "ما هو تكافل وكرامة؟",
    "متى تكافل وكرامة {{nextYear}}؟",
    "كيف أصرف تكافل وكرامة؟"
  ],
  "differentiationIdeas": [
    "تحويل أخبار شهرية متفرقة إلى مرجع دائم سهل البحث",
    "تبسيط النمط الشهري من دون تعميم مضلل",
    "إضافة FAQ عملية عن قنوات الصرف والتفريق بين الزيادة والموعد",
    "جواب مباشر عن موعد تكافل وكرامة (مصر) في بداية الصفحة قبل أي شرح إضافي.",
    "محتوى عربي يشرح المعنى والسياق بدلاً من الاكتفاء بعداد أو تاريخ مختصر.",
    "أسئلة شائعة عملية تساعد القارئ على فهم تكافل وكرامة (مصر) والتصرف بناءً عليه."
  ],
  "factSources": [
    {
      "label": "وزارة التضامن الاجتماعي: صرف تكافل وكرامة عن شهر يناير",
      "url": "https://www.moss.gov.eg/Sites/MOSA/ar-eg/Pages/news-details.aspx?nid=3804"
    },
    {
      "label": "وزارة التضامن الاجتماعي: صرف تكافل وكرامة عن شهر فبراير",
      "url": "https://www.moss.gov.eg/ar-eg/Pages/news-details.aspx?nid=3885"
    },
    {
      "label": "وزارة التضامن الاجتماعي: صرف تكافل وكرامة عن شهر مارس",
      "url": "https://www.moss.gov.eg/ar-eg/Pages/news-details.aspx?nid=4637"
    }
  ],
  "notes": "SERP العربي حول تكافل وكرامة ضوضائي جداً، لكن بيانات وزارة التضامن تمنح نمطاً واضحاً يمكن البناء عليه. لذلك صيغت الصفحة لتكون مرجعاً زمنياً وخدمياً لا مجرد خبر موسمي."
}
