[
  {
    "city_slug": "dodoma",
    "city_name_ar": "دودوما",
    "city_name_en": "Dodoma",
    "country_slug": "tanzania",
    "country_code": "TZ",
    "country_name_ar": "تنزانيا",
    "country_name_en": "Tanzania",
    "timezone": "Africa/Dar_es_Salaam",
    "lat": -6.17221,
    "lon": 35.73947,
    "is_capital": true,
    "priority": 765179,
    "population": 765179
  },
  {
    "city_slug": "dar-es-salaam",
    "city_name_ar": "دار السلام",
    "city_name_en": "Dar es Salaam",
    "country_slug": "tanzania",
    "country_code": "TZ",
    "country_name_ar": "تنزانيا",
    "country_name_en": "Tanzania",
    "timezone": "Africa/Dar_es_Salaam",
    "lat": -6.82349,
    "lon": 39.26951,
    "is_capital": false,
    "priority": 5383728,
    "population": 5383728
  },
  {
    "city_slug": "mwanza",
    "city_name_ar": "موانزا",
    "city_name_en": "Mwanza",
    "country_slug": "tanzania",
    "country_code": "TZ",
    "country_name_ar": "تنزانيا",
    "country_name_en": "Tanzania",
    "timezone": "Africa/Dar_es_Salaam",
    "lat": -2.51667,
    "lon": 32.9,
    "is_capital": false,
    "priority": 1104521,
    "population": 1104521
  },
  {
    "city_slug": "zanzibar",
    "city_name_ar": "مدينة زنجبار",
    "city_name_en": "Zanzibar",
    "country_slug": "tanzania",
    "country_code": "TZ",
    "country_name_ar": "تنزانيا",
    "country_name_en": "Tanzania",
    "timezone": "Africa/Dar_es_Salaam",
    "lat": -6.16394,
    "lon": 39.19793,
    "is_capital": false,
    "priority": 709809,
    "population": 709809
  },
  {
    "city_slug": "arusha",
    "city_name_ar": "أروشا",
    "city_name_en": "Arusha",
    "country_slug": "tanzania",
    "country_code": "TZ",
    "country_name_ar": "تنزانيا",
    "country_name_en": "Tanzania",
    "timezone": "Africa/Dar_es_Salaam",
    "lat": -3.36667,
    "lon": 36.68333,
    "is_capital": false,
    "priority": 617631,
    "population": 617631
  }
]
