{
  "slug": "world-cup-2030",
  "locale": "ar",
  "capturedAt": "2026-07-07T08:30:03.139Z",
  "primaryQueries": [
    "كم باقي على كأس العالم 2030",
    "متى كأس العالم في المغرب",
    "موعد كأس العالم 2030",
    "الدول المستضيفة لكأس العالم 2030",
    "مباريات كأس العالم 2030 في أمريكا الجنوبية",
    "متى نهائي كأس العالم 2030",
    "أول استضافة عربية لكأس العالم",
    "هل المغرب سيستضيف كأس العالم",
    "متى أعلن عن استضافة المغرب لكأس العالم",
    "لماذا تقام مباريات في الأوروغواي بكأس العالم 2030"
  ],
  "competitors": [
    {
      "site": "fifa.com",
      "type": "official",
      "url": "https://www.fifa.com/ar/tournaments/mens/worldcup/articles/world-cup-2030-hosts-qualified-bidding-spain-argentina-morocco-uruguay-portugal-paraguay-ar",
      "focus": [
        "المصدر الرسمي الأقوى: كل تفاصيل البطولة من الفيفا مباشرة"
      ],
      "gaps": [
        "محتوى مرجعي عام، لا عداد تنازلي"
      ]
    },
    {
      "site": "ar.wikipedia.org",
      "type": "reference",
      "url": "https://ar.wikipedia.org/wiki/كأس_العالم_2030",
      "focus": [
        "مرجع شامل عن تفاصيل البطولة والترشيح"
      ],
      "gaps": [
        "مرجع عام غير محدث بعداد تنازلي حي"
      ]
    },
    {
      "site": "skynewsarabia.com",
      "type": "arabic-competitor",
      "url": "https://www.skynewsarabia.com/sport/1761469",
      "focus": [
        "تغطية إعلامية دقيقة لإعلان الاستضافة الرسمي"
      ],
      "gaps": [
        "خبر لحظي بتاريخ الإعلان، ليس صفحة عد تنازلي دائمة"
      ]
    },
    {
      "site": "alarabiya.net",
      "type": "arabic-competitor",
      "url": "https://www.alarabiya.net/sport/2024/12/11/ملف-المغرب-واسبانيا-والبرتغال-يفوز-باستضافة-كأس-العالم-2030",
      "focus": [
        "تفاصيل فوز الملف المشترك بالتزكية"
      ],
      "gaps": [
        "مقال إخباري تاريخي، لا يتابع الموعد المستقبلي بعداد"
      ]
    },
    {
      "site": "rahhal.wego.com",
      "type": "arabic-competitor",
      "url": "https://rahhal.wego.com/blog/دليلك-إلى-كأس-العالم-2030-مواعيد/",
      "focus": [
        "دليل سياحي يذكر الدول المستضيفة والملاعب"
      ],
      "gaps": [
        "موجه للسياحة، لا يركز على الموعد الدقيق أو عداد تنازلي"
      ]
    },
    {
      "site": "kooora.com",
      "type": "arabic-competitor",
      "url": "https://www.kooora.com/كرة-قدم/أخبار/رسميا-اقامة-مونديال-2030",
      "focus": [
        "تغطية رياضية عربية شهيرة للحدث"
      ],
      "gaps": [
        "خبر إخباري، لا محتوى دائم أو عداد تنازلي"
      ]
    }
  ],
  "coverageMatrix": [
    {
      "keyword": "كم باقي على كأس العالم 2030",
      "whyItMatters": "نية العد التنازلي الأساسية طويلة المدى (4 سنوات مقبلة)"
    },
    {
      "keyword": "متى كأس العالم في المغرب",
      "whyItMatters": "صياغة شائعة تربط البطولة بالمغرب تحديداً"
    },
    {
      "keyword": "ما هي الدول المستضيفة لكأس العالم 2030",
      "whyItMatters": "نية معلوماتية أساسية حول الدول الثلاث الرئيسية"
    },
    {
      "keyword": "لماذا تقام مباريات في أمريكا الجنوبية بكأس العالم 2030",
      "whyItMatters": "تفصيل فريد ومثير للفضول حول الذكرى المئوية"
    },
    {
      "keyword": "هل هذه أول استضافة عربية أو أفريقية لكأس العالم",
      "whyItMatters": "زاوية فخر إقليمي تُبحث بكثرة في السياق المغربي والعربي"
    },
    {
      "keyword": "متى أعلن رسمياً عن استضافة المغرب لكأس العالم 2030",
      "whyItMatters": "تفصيل تاريخي يعزز مصداقية الصفحة"
    },
    {
      "keyword": "متى نهائي كأس العالم 2030",
      "whyItMatters": "يمنح القارئ أفقاً كاملاً للبطولة الطويلة (45 يوماً)"
    },
    {
      "keyword": "كيف أتابع فرق التوقيت مع دول الاستضافة",
      "whyItMatters": "نية عملية لجمهور يتابع بطولة موزعة على ثلاث قارات وتوقيتات مختلفة"
    }
  ],
  "keywordGaps": [
    "لا توجد صفحة عربية واحدة بعداد تنازلي حي طويل المدى لكأس العالم 2030",
    "لا تشرح أغلب الصفحات بوضوح سبب إقامة مباريات في أمريكا الجنوبية رغم أن الاستضافة الرئيسية في المغرب وأوروبا",
    "لا تبرز أي صفحة بما يكفي زاوية 'أول استضافة عربية وأفريقية' كنقطة فخر وتفرد",
    "أغلب المحتوى مقالات إخبارية تاريخية عن إعلان الاستضافة، لا صفحات متجددة تتابع الموعد",
    "لا يوجد ربط بمحتوى الموقع الآخر ذي الصلة بالمغرب (الوقت الآن، فرق التوقيت)",
    "لا تجمع أي صفحة حقيقة كون هذه أطول نسخة في تاريخ البطولة (45 يوماً) مع باقي التفاصيل",
    "لا تشرح أي صفحة بوضوح تعقيد فرق التوقيت بين قارات الاستضافة الثلاث للمتابعين من خارج المنطقة",
    "لا تربط أي صفحة الموعد بمواقيت الصلاة أو الوقت الحالي في مدن الاستضافة المغربية"
  ],
  "unansweredQuestions": [
    "متى بالضبط تبدأ وتنتهي البطولة؟",
    "ما هي الدول المستضيفة بالتحديد؟",
    "لماذا تقام مباريات في أمريكا الجنوبية أيضاً؟",
    "هل هذه أول مرة يستضيف فيها بلد عربي كأس العالم؟",
    "متى أُعلن رسمياً عن هذا القرار؟",
    "كيف أتابع فرق التوقيت مع دول الاستضافة المختلفة؟"
  ],
  "differentiationIdeas": [
    "عداد تنازلي حي طويل المدى (4 سنوات) بدل مقالات إخبارية تاريخية عن يوم الإعلان فقط",
    "شرح واضح لسبب إقامة مباريات الذكرى المئوية في أمريكا الجنوبية — تفصيل فريد يفوّته أغلب المحتوى العربي",
    "إبراز زاوية الفخر الإقليمي (أول استضافة عربية وأفريقية) بوضوح أكبر من المصادر الإخبارية العابرة",
    "ربط الصفحة بمحتوى الموقع الآخر (الوقت الآن في المغرب، حاسبة فرق التوقيت) يخدم استمرارية الزيارة",
    "استخدام حقل retirement لضمان اختفاء الصفحة تلقائياً بعد انتهاء البطولة في 2030 بدل عداد خاطئ للنسخة القادمة بعد 4 سنوات"
  ],
  "factSources": [
    {
      "label": "الفيفا — كأس العالم 2030: كل شيء عن البطولة",
      "url": "https://www.fifa.com/ar/tournaments/mens/worldcup/articles/world-cup-2030-hosts-qualified-bidding-spain-argentina-morocco-uruguay-portugal-paraguay-ar"
    },
    {
      "label": "سكاي نيوز عربية — رسمياً كأس العالم 2030 في المغرب وإسبانيا والبرتغال",
      "url": "https://www.skynewsarabia.com/sport/1761469-رسميا-كاأس-العالم-2030-المغرب-واسبانيا-والبرتغال"
    },
    {
      "label": "العربية — ملف المغرب والبرتغال وإسبانيا يفوز باستضافة كأس العالم 2030",
      "url": "https://www.alarabiya.net/sport/2024/12/11/ملف-المغرب-واسبانيا-والبرتغال-يفوز-باستضافة-كأس-العالم-2030"
    }
  ],
  "notes": "الموعد (8 يونيو - 21 يوليو 2030) والدول المستضيفة تم التحقق منها من مصدرين مستقلين متطابقين (fifa.com والعربية/سكاي نيوز). بما أن الحدث بعيد 4 سنوات كاملة عن تاريخ البناء، استُخدم core.date كتاريخ حرفي ثابت '2030-06-08' بدل قالب {{year}}، لأن محرك التواريخ (nextEstimated) يُرحّل الموعد بمقدار سنة واحدة فقط عند المرور، وهذا غير كافٍ لتغطية فجوة 4 سنوات — التاريخ الحرفي الثابت هو الطريقة الصحيحة الوحيدة هنا. رغم ذلك، استُخدمت رموز {{year}} داخل نص المحتوى (وليس في core.date) لأن آلية القراءة الفعلية (resolveEventMeta) تستخرج السنة من التاريخ المستهدف المحسوب فعلياً (2030) وليس من السنة الحالية عند العرض، فتظل النصوص صحيحة طوال فترة العد التنازلي الأربع سنوات. أُضيف حقل retirement (afterDate: 2030-09-01) لأن النسخة القادمة من كأس العالم ستكون في بلد مختلف تماماً بعد 4 سنوات أخرى."
}
